structurefinder/__init__.py
structurefinder/strf.py
structurefinder/strf_cmd.py
structurefinder/ccdc/__init__.py
structurefinder/ccdc/query.py
structurefinder/cgi_ui/__init__.py
structurefinder/cgi_ui/bottle.py
structurefinder/cgi_ui/strf_web.py
structurefinder/cgi_ui/static/favicon.ico
structurefinder/cgi_ui/static/strf_web.css
structurefinder/cgi_ui/static/strf_web.js
structurefinder/cgi_ui/static/strf_web_csd.js
structurefinder/cgi_ui/static/bootstrap-3.3.7/custom.css
structurefinder/cgi_ui/static/bootstrap-3.3.7/css/bootstrap-theme.css
structurefinder/cgi_ui/static/bootstrap-3.3.7/css/bootstrap-theme.css.map
structurefinder/cgi_ui/static/bootstrap-3.3.7/css/bootstrap-theme.min.css
structurefinder/cgi_ui/static/bootstrap-3.3.7/css/bootstrap-theme.min.css.map
structurefinder/cgi_ui/static/bootstrap-3.3.7/css/bootstrap.css
structurefinder/cgi_ui/static/bootstrap-3.3.7/css/bootstrap.css.map
structurefinder/cgi_ui/static/bootstrap-3.3.7/css/bootstrap.min.css
structurefinder/cgi_ui/static/bootstrap-3.3.7/css/bootstrap.min.css.map
structurefinder/cgi_ui/static/bootstrap-3.3.7/css/font-awesome.css
structurefinder/cgi_ui/static/bootstrap-3.3.7/fonts/FontAwesome.otf
structurefinder/cgi_ui/static/bootstrap-3.3.7/fonts/fontawesome-webfont.eot
structurefinder/cgi_ui/static/bootstrap-3.3.7/fonts/fontawesome-webfont.svg
structurefinder/cgi_ui/static/bootstrap-3.3.7/fonts/fontawesome-webfont.ttf
structurefinder/cgi_ui/static/bootstrap-3.3.7/fonts/fontawesome-webfont.woff
structurefinder/cgi_ui/static/bootstrap-3.3.7/fonts/glyphicons-halflings-regular.eot
structurefinder/cgi_ui/static/bootstrap-3.3.7/fonts/glyphicons-halflings-regular.svg
structurefinder/cgi_ui/static/bootstrap-3.3.7/fonts/glyphicons-halflings-regular.ttf
structurefinder/cgi_ui/static/bootstrap-3.3.7/fonts/glyphicons-halflings-regular.woff
structurefinder/cgi_ui/static/bootstrap-3.3.7/fonts/glyphicons-halflings-regular.woff2
structurefinder/cgi_ui/static/bootstrap-3.3.7/js/bootstrap.js
structurefinder-87.dist-info/METADATA
structurefinder-87.dist-info/WHEEL
structurefinder-87.dist-info/entry_points.txt
structurefinder-87.dist-info/licenses/LICENSE
structurefinder-87.dist-info/RECORD
